Metadata-Version: 2.1
Name: snookerprofile
Version: 0.0.1
Summary: Snooker Profile Learning by Snooker Patcharee
Home-page: https://github.com/Snookerpatcharee/snookerprofile
Author: Snooker Patcharee
Author-email: snooker.nnnn@gmail.com
License: MIT
Download-URL: https://github.com/Snookerpatcharee/snookerprofile/archive/v0.0.1.zip
Keywords: snooker,profile,Snooker Patcharee
Platform: UNKNOWN
Classifier: Development Status :: 3 - Alpha
Classifier: Intended Audience :: Education
Classifier: Topic :: Utilities
Classifier: License :: OSI Approved :: MIT License
Classifier: Programming Language :: Python :: 3
Classifier: Programming Language :: Python :: 3.4
Classifier: Programming Language :: Python :: 3.5
Classifier: Programming Language :: Python :: 3.6
Classifier: Programming Language :: Python :: 3.7
Classifier: Programming Language :: Python :: 3.8
Classifier: Programming Language :: Python :: 3.9
Classifier: Programming Language :: Python :: 3.10
License-File: LICENSE.txt
